{
    "漏洞标题": "厦门天锐科技股份有限公司天锐绿盾审批系统存在文件上传漏洞",
    "CNVD-ID": "CNVD-2025-01244",
    "公开日期": "2025-01-25",
    "危害级别": "中",
    "影响产品": "厦门天锐科技股份有限公司 天锐绿盾审批系统",
    "漏洞描述": "天锐绿盾审批系统‌是一种集成在OA系统中的加密软件，主要用于实现审批流程的自动化和信息化。\n厦门天锐科技股份有限公司天锐绿盾审批系统存在文件上传漏洞，攻击者可利用该漏洞上传恶意文件，获取服务器权限。",
    "漏洞类型": "通用型漏洞",
    "参考链接": "",
    "漏洞解决方案": "厂商已发布最新版本修复漏洞，请广大用户及时下载更新：\nhttps://www.tipray.com",
    "厂商补丁": "https://www.cnvd.org.cn/patchInfo/show/651446",
    "验证信息": "已验证",
    "报送时间": "2024-12-11",
    "收录时间": "2025-01-14",
    "更新时间": "2025-01-14",
    "漏洞附件": "附件暂不公开"
}