{
    "漏洞标题": "Travel Management System存在SQL注入漏洞",
    "CNVD-ID": "CNVD-2025-03970",
    "公开日期": "2025-02-22",
    "危害级别": "中",
    "影响产品": "Travel Management System Travel Management System",
    "漏洞描述": "Travel Management System是一款开源的旅游管理系统。\nTravel Management System Travel Management System存在SQL注入漏洞，攻击者可利用该漏洞获取数据库敏感信息。",
    "漏洞类型": "通用型漏洞",
    "参考链接": "",
    "漏洞解决方案": "暂无",
    "厂商补丁": "",
    "验证信息": "已验证",
    "报送时间": "2025-01-08",
    "收录时间": "2025-02-28",
    "更新时间": "2025-02-28",
    "漏洞附件": "附件暂不公开"
}